O/__init__.py
O/outliersArsh.py
arshkawatra-0.0.3.dist-info/LICENSE.txt
arshkawatra-0.0.3.dist-info/METADATA
arshkawatra-0.0.3.dist-info/WHEEL
arshkawatra-0.0.3.dist-info/entry_points.txt
arshkawatra-0.0.3.dist-info/top_level.txt
arshkawatra-0.0.3.dist-info/RECORD
