Metadata-Version: 2.1
Name: arshkawatra
Version: 0.0.3
Summary: Outliers
Home-page: 
Author: Arshdeep Kawatra
Author-email: akawatra_be17@thapar.edu
License: UNKNOWN
Platform: UNKNOWN
Classifier: Programming Language :: Python :: 3
Classifier: License :: OSI Approved :: MIT License
Classifier: Operating System :: OS Independent
Requires-Python: >=3.6
Requires-Dist: requests
